README.md
setup.py
pandas_transform_checker/__init__.py
pandas_transform_checker/decorator_contract_checker.py
pandas_transform_checker.egg-info/PKG-INFO
pandas_transform_checker.egg-info/SOURCES.txt
pandas_transform_checker.egg-info/dependency_links.txt
pandas_transform_checker.egg-info/requires.txt
pandas_transform_checker.egg-info/top_level.txt