Metadata-Version: 2.1
Name: pandas-transform-checker
Version: 0.1
Summary: function annotations to check properties on pandas dataframe transformations
Home-page: https://github.com/thib-s/pandas_transform_checker
Author: thibaut boissin
Author-email: thibaut.boissin@gmail.com
License: BSD 3-Clause License
Platform: UNKNOWN
Classifier: Programming Language :: Python :: 3
Classifier: Operating System :: OS Independent
